drf_advanced_token/__init__.py
drf_advanced_token/admin.py
drf_advanced_token/apps.py
drf_advanced_token/models.py
drf_advanced_token/tests.py
drf_advanced_token/urls.py
drf_advanced_token/views.py
drf_advanced_token/management/__init__.py
drf_advanced_token/management/commands/__init__.py
drf_advanced_token/management/commands/revoke_all_tokens.py
drf_advanced_token/middleware/__init__.py
drf_advanced_token/middleware/auth.py
drf_advanced_token/migrations/__init__.py
django_drf_advanced_token-2.1.0.dist-info/LICENSE
django_drf_advanced_token-2.1.0.dist-info/METADATA
django_drf_advanced_token-2.1.0.dist-info/WHEEL
django_drf_advanced_token-2.1.0.dist-info/top_level.txt
django_drf_advanced_token-2.1.0.dist-info/RECORD
