Metadata-Version: 2.1
Name: django-drf-advanced-token
Version: 2.1.0
Summary: More advanced features for the Django Rest Framework rest_framework.authtoken app
Home-page: https://github.com/amp89/drf_advanced_token
Author: Alex Peterson
Author-email: contact@alexpeterson.tech
License: MIT
Download-URL: https://github.com/amp89/drf_advanced_token/archive/2.1.0.tar.gz
Platform: UNKNOWN
Requires-Python: >=3.6
Requires-Dist: django
Requires-Dist: djangorestframework
